perimeterx/__init__.py
perimeterx/fingerprint.py
perimeterx/key_map.json
perimeterx/mods.py
perimeterx/pc_functions.py
perimeterx/solve.py
perimeterx-1.1.2.dist-info/LICENSE
perimeterx-1.1.2.dist-info/METADATA
perimeterx-1.1.2.dist-info/WHEEL
perimeterx-1.1.2.dist-info/RECORD
