Metadata-Version: 2.3
Name: perimeterx
Version: 1.1.2
Summary: Solves PerimeterX challenge and grabs cookies
License: Apache-2.0
Author: Troy Henson
Author-email: thenson@gmail.com
Requires-Python: >=3.10
Classifier: Development Status :: 5 - Production/Stable
Classifier: Intended Audience :: Developers
Classifier: License :: OSI Approved :: Apache Software License
Classifier: Natural Language :: English
Classifier: Programming Language :: Python :: 3
Classifier: Programming Language :: Python :: 3.10
Classifier: Programming Language :: Python :: 3.11
Classifier: Programming Language :: Python :: 3.12
Classifier: Programming Language :: Python :: 3.13
Classifier: Topic :: Software Development :: Libraries
Requires-Dist: tls_client (>=1.0.1,<2.0.0)
Requires-Dist: typing_extensions (>=4.12.2,<5.0.0)
Requires-Dist: wgl (>=0.4.6,<0.5.0)
Project-URL: Documentation, https://pypi.org/project/perimeterx
Project-URL: Homepage, https://pypi.org/project/perimeterx
Project-URL: Source, https://pypi.org/project/perimeterx/#files
